k_bot/__init__.py
k_bot/bots.py
k_bot/users.py
k_bot-3.0.dist-info/METADATA
k_bot-3.0.dist-info/WHEEL
k_bot-3.0.dist-info/top_level.txt
k_bot-3.0.dist-info/RECORD
