Metadata-Version: 2.1
Name: k-bot
Version: 3.0
Summary: 한국 디스코드봇 리스트 api를 더욱 쉽게! | Korean Discord bot list api easier!
Home-page: https://github.com/5-23/k_bot/tree/main
Author: 5-23
Author-email: yhanbyeol6@gmail.com
License: UNKNOWN
Download-URL: https://github.com/5-23/k_bot/tree/main
Keywords: bot,study,api
Platform: UNKNOWN
Classifier: Programming Language :: Python :: 3
Classifier: Programming Language :: Python :: 3.2
Classifier: Programming Language :: Python :: 3.3
Classifier: Programming Language :: Python :: 3.4
Classifier: Programming Language :: Python :: 3.5
Classifier: Programming Language :: Python :: 3.6
Requires-Python: >=3
Requires-Dist: requests
